Workbook

Sheet Assumptions
A1: CERBYL COST MODEL ASSUMPTIONS
A2: Parameter | B2: Value | C2: Notes / Source
A3: AI Token Assumptions
A4: Best-case tokens per user per month | B4: 500000 | C4: Active student: flashcards, quiz, ask, podcast mix
A5: Worst-case tokens per user per month | B5: 3000000 | C5: Heavy user: media notes + repeated podcast sessions
A6: Fast model cost per token (Gemini 2.0 Flash) | B6: 1.5e-07 | C6: Gemini 2.0 Flash blended input+output ~$0.15 per 1M tokens. Used for: ask_simple, flashcards_ai, quiz_ai, podcast_ai, learning_path_ai
A7: Premium model cost per token (Gemini 1.5 Pro) | B7: 2.5e-06 | C7: Gemini 1.5 Pro blended input+output ~$2.50 per 1M tokens. Used for: media_notes_ai heavy sessions and complex multi-agent chains in worst case
A8: % tokens on fast model (best case) | B8: 0.95 | C8: 95% Gemini 2.0 Flash (cheap fast model), 5% Gemini 1.5 Pro for media notes only
A9: % tokens on fast model (worst case) | B9: 0.7 | C9: 70% Gemini 2.0 Flash, 30% Gemini 1.5 Pro for heavy media notes and multi-agent worst case usage
A10: Compute and Storage
A11: GB processed per user per month | B11: 0.1 | C11: 100 MB avg - AWS EC2 + Lambda blended
A12: Cost per GB processed ($) | B12: 1.13 | C12: AWS blended compute rate
A13: GB stored per user per month | B13: 1 | C13: ChromaDB + PostgreSQL per user
A14: Cost per GB stored ($) | B14: 0.045 | C14: S3 + RDS blended
A15: Bandwidth
A16: GB egress per user per month | B16: 0.5 | C16: API + frontend CDN traffic
A17: Cost per GB egress ($) | B17: 0.09 | C17: AWS CloudFront standard
A18: Software Licenses
A19: Base SaaS licenses per month ($) | B19: 750 | C19: GitHub, Figma, monitoring, Jira
A20: Users per license tier | B20: 5000 | C20: Add $750 per additional 5,000 users
A21: Headcount
A22: FTEs per 5,000 users | B22: 2 | C22: 1 eng + 1 support
A23: Annual cost per FTE ($) | B23: 28571 | C23: 2 lakh INR per month at 84 INR/USD
A24: Admin and compliance annual ($) | B24: 20000 | C24: Legal, accounting, misc
A25: Hardware
A26: Laptop budget per FTE ($) | B26: 2000 | C26: Amortized over 36 months
A27: Facilities
A28: Monthly facilities per 5K users ($) | B28: 2500 | C28: Co-working, cloud-first
A29: Pricing
A30: Pro plan monthly charge ($) | B30: 15 | C30: Best case ARPU — under ChatGPT, beats Quizlet
A31: Power plan monthly charge ($) | B31: 25 | C31: Worst case ARPU — heavy users, 500K+ tokens
A32: Free trial months | B32: 2 | C32: 2 months free on annual plan

Sheet Margin Trend
A1: CERBYL MARGIN TREND BY USER SCALE
C2: BEST CASE (500K tokens/user/mo) Pro $15/mo | I2: WORST CASE (3M tokens/user/mo) Power $25/mo
A3: Cost Category | B3: Per-User Driver | C3: 1,000 Users | D3: 5,000 Users | E3: 10,000 Users | F3: 25,000 Users | G3: 50,000 Users | I3: 1,000 Users | J3: 5,000 Users | K3: 10,000 Users | L3: 25,000 Users | M3: 50,000 Users
A4: AI Tokens (Haiku + Sonnet blended) | B4: tokens x blended cost/token x users | C4: =(1000*Assumptions!B4)*(Assumptions!B8*Assumptions!B6+(1-Assumptions!B8)*Assumptions!B7) -> 133.75 | D4: =(5000*Assumptions!B4)*(Assumptions!B8*Assumptions!B6+(1-Assumptions!B8)*Assumptions!B7) -> 668.75 | E4: =(10000*Assumptions!B4)*(Assumptions!B8*Assumptions!B6+(1-Assumptions!B8)*Assumptions!B7) -> 1337.5 | F4: =(25000*Assumptions!B4)*(Assumptions!B8*Assumptions!B6+(1-Assumptions!B8)*Assumptions!B7) -> 3343.75 | G4: =(50000*Assumptions!B4)*(Assumptions!B8*Assumptions!B6+(1-Assumptions!B8)*Assumptions!B7) -> 6687.5 | I4: =(1000*Assumptions!B5)*(Assumptions!B9*Assumptions!B6+(1-Assumptions!B9)*Assumptions!B7) -> 2565 | J4: =(5000*Assumptions!B5)*(Assumptions!B9*Assumptions!B6+(1-Assumptions!B9)*Assumptions!B7) -> 12825 | K4: =(10000*Assumptions!B5)*(Assumptions!B9*Assumptions!B6+(1-Assumptions!B9)*Assumptions!B7) -> 25650 | L4: =(25000*Assumptions!B5)*(Assumptions!B9*Assumptions!B6+(1-Assumptions!B9)*Assumptions!B7) -> 64125 | M4: =(50000*Assumptions!B5)*(Assumptions!B9*Assumptions!B6+(1-Assumptions!B9)*Assumptions!B7) -> 128250
A5: Compute and Processing | B5: GB processed x cost/GB x users | C5: =1000*Assumptions!B11*Assumptions!B12 -> 113 | D5: =5000*Assumptions!B11*Assumptions!B12 -> 565 | E5: =10000*Assumptions!B11*Assumptions!B12 -> 1130 | F5: =25000*Assumptions!B11*Assumptions!B12 -> 2825 | G5: =50000*Assumptions!B11*Assumptions!B12 -> 5650 | I5: =1000*Assumptions!B11*Assumptions!B12 -> 113 | J5: =5000*Assumptions!B11*Assumptions!B12 -> 565 | K5: =10000*Assumptions!B11*Assumptions!B12 -> 1130 | L5: =25000*Assumptions!B11*Assumptions!B12 -> 2825 | M5: =50000*Assumptions!B11*Assumptions!B12 -> 5650
A6: Storage and Databases | B6: GB stored x cost/GB x users | C6: =1000*Assumptions!B13*Assumptions!B14 -> 45 | D6: =5000*Assumptions!B13*Assumptions!B14 -> 225 | E6: =10000*Assumptions!B13*Assumptions!B14 -> 450 | F6: =25000*Assumptions!B13*Assumptions!B14 -> 1125 | G6: =50000*Assumptions!B13*Assumptions!B14 -> 2250 | I6: =1000*Assumptions!B13*Assumptions!B14 -> 45 | J6: =5000*Assumptions!B13*Assumptions!B14 -> 225 | K6: =10000*Assumptions!B13*Assumptions!B14 -> 450 | L6: =25000*Assumptions!B13*Assumptions!B14 -> 1125 | M6: =50000*Assumptions!B13*Assumptions!B14 -> 2250
A7: Bandwidth and CDN | B7: GB egress x cost/GB x users | C7: =1000*Assumptions!B16*Assumptions!B17 -> 45 | D7: =5000*Assumptions!B16*Assumptions!B17 -> 225 | E7: =10000*Assumptions!B16*Assumptions!B17 -> 450 | F7: =25000*Assumptions!B16*Assumptions!B17 -> 1125 | G7: =50000*Assumptions!B16*Assumptions!B17 -> 2250 | I7: =1000*Assumptions!B16*Assumptions!B17 -> 45 | J7: =5000*Assumptions!B16*Assumptions!B17 -> 225 | K7: =10000*Assumptions!B16*Assumptions!B17 -> 450 | L7: =25000*Assumptions!B16*Assumptions!B17 -> 1125 | M7: =50000*Assumptions!B16*Assumptions!B17 -> 2250
A8: Software Licenses | B8: Flat, scales per 5K users | C8: =ROUNDUP(1000/Assumptions!B20,0)*Assumptions!B19 -> 750 | D8: =ROUNDUP(5000/Assumptions!B20,0)*Assumptions!B19 -> 750 | E8: =ROUNDUP(10000/Assumptions!B20,0)*Assumptions!B19 -> 1500 | F8: =ROUNDUP(25000/Assumptions!B20,0)*Assumptions!B19 -> 3750 | G8: =ROUNDUP(50000/Assumptions!B20,0)*Assumptions!B19 -> 7500 | I8: =ROUNDUP(1000/Assumptions!B20,0)*Assumptions!B19 -> 750 | J8: =ROUNDUP(5000/Assumptions!B20,0)*Assumptions!B19 -> 750 | K8: =ROUNDUP(10000/Assumptions!B20,0)*Assumptions!B19 -> 1500 | L8: =ROUNDUP(25000/Assumptions!B20,0)*Assumptions!B19 -> 3750 | M8: =ROUNDUP(50000/Assumptions!B20,0)*Assumptions!B19 -> 7500
A9: Salary (Eng and Support) | B9: 2 FTEs per 5K users, 2 lakh INR | C9: =ROUNDUP(1000/Assumptions!B20,0)*Assumptions!B22*Assumptions!B23/12 -> 4761.8333 | D9: =ROUNDUP(5000/Assumptions!B20,0)*Assumptions!B22*Assumptions!B23/12 -> 4761.8333 | E9: =ROUNDUP(10000/Assumptions!B20,0)*Assumptions!B22*Assumptions!B23/12 -> 9523.6667 | F9: =ROUNDUP(25000/Assumptions!B20,0)*Assumptions!B22*Assumptions!B23/12 -> 23809.167 | G9: =ROUNDUP(50000/Assumptions!B20,0)*Assumptions!B22*Assumptions!B23/12 -> 47618.333 | I9: =ROUNDUP(1000/Assumptions!B20,0)*Assumptions!B22*Assumptions!B23/12 -> 4761.8333 | J9: =ROUNDUP(5000/Assumptions!B20,0)*Assumptions!B22*Assumptions!B23/12 -> 4761.8333 | K9: =ROUNDUP(10000/Assumptions!B20,0)*Assumptions!B22*Assumptions!B23/12 -> 9523.6667 | L9: =ROUNDUP(25000/Assumptions!B20,0)*Assumptions!B22*Assumptions!B23/12 -> 23809.167 | M9: =ROUNDUP(50000/Assumptions!B20,0)*Assumptions!B22*Assumptions!B23/12 -> 47618.333
A10: Laptops and Equipment | B10: Amortized per FTE over 36 months | C10: =ROUNDUP(1000/Assumptions!B20,0)*Assumptions!B22*Assumptions!B26/36 -> 111.11111 | D10: =ROUNDUP(5000/Assumptions!B20,0)*Assumptions!B22*Assumptions!B26/36 -> 111.11111 | E10: =ROUNDUP(10000/Assumptions!B20,0)*Assumptions!B22*Assumptions!B26/36 -> 222.22222 | F10: =ROUNDUP(25000/Assumptions!B20,0)*Assumptions!B22*Assumptions!B26/36 -> 555.55556 | G10: =ROUNDUP(50000/Assumptions!B20,0)*Assumptions!B22*Assumptions!B26/36 -> 1111.1111 | I10: =ROUNDUP(1000/Assumptions!B20,0)*Assumptions!B22*Assumptions!B26/36 -> 111.11111 | J10: =ROUNDUP(5000/Assumptions!B20,0)*Assumptions!B22*Assumptions!B26/36 -> 111.11111 | K10: =ROUNDUP(10000/Assumptions!B20,0)*Assumptions!B22*Assumptions!B26/36 -> 222.22222 | L10: =ROUNDUP(25000/Assumptions!B20,0)*Assumptions!B22*Assumptions!B26/36 -> 555.55556 | M10: =ROUNDUP(50000/Assumptions!B20,0)*Assumptions!B22*Assumptions!B26/36 -> 1111.1111
A11: Compliance and Admin | B11: Annual admin divided by 12 | C11: =Assumptions!B24/12 -> 1666.6667 | D11: =Assumptions!B24/12 -> 1666.6667 | E11: =Assumptions!B24/12 -> 1666.6667 | F11: =Assumptions!B24/12 -> 1666.6667 | G11: =Assumptions!B24/12 -> 1666.6667 | I11: =Assumptions!B24/12 -> 1666.6667 | J11: =Assumptions!B24/12 -> 1666.6667 | K11: =Assumptions!B24/12 -> 1666.6667 | L11: =Assumptions!B24/12 -> 1666.6667 | M11: =Assumptions!B24/12 -> 1666.6667
A12: Facilities | B12: 2,500 per month per 5K users | C12: =ROUNDUP(1000/Assumptions!B20,0)*Assumptions!B28 -> 2500 | D12: =ROUNDUP(5000/Assumptions!B20,0)*Assumptions!B28 -> 2500 | E12: =ROUNDUP(10000/Assumptions!B20,0)*Assumptions!B28 -> 5000 | F12: =ROUNDUP(25000/Assumptions!B20,0)*Assumptions!B28 -> 12500 | G12: =ROUNDUP(50000/Assumptions!B20,0)*Assumptions!B28 -> 25000 | I12: =ROUNDUP(1000/Assumptions!B20,0)*Assumptions!B28 -> 2500 | J12: =ROUNDUP(5000/Assumptions!B20,0)*Assumptions!B28 -> 2500 | K12: =ROUNDUP(10000/Assumptions!B20,0)*Assumptions!B28 -> 5000 | L12: =ROUNDUP(25000/Assumptions!B20,0)*Assumptions!B28 -> 12500 | M12: =ROUNDUP(50000/Assumptions!B20,0)*Assumptions!B28 -> 25000
A13: Total Cost per Month | C13: =SUM(C4:C12) -> 10126.361 | D13: =SUM(D4:D12) -> 11473.361 | E13: =SUM(E4:E12) -> 21280.056 | F13: =SUM(F4:F12) -> 50700.139 | G13: =SUM(G4:G12) -> 99733.611 | I13: =SUM(I4:I12) -> 12557.611 | J13: =SUM(J4:J12) -> 23629.611 | K13: =SUM(K4:K12) -> 45592.556 | L13: =SUM(L4:L12) -> 111481.39 | M13: =SUM(M4:M12) -> 221296.11
A15: UNIT ECONOMICS
A16: Cost per User per Month | C16: =C13/1000 -> 10.126361 | D16: =D13/5000 -> 2.2946722 | E16: =E13/10000 -> 2.1280056 | F16: =F13/25000 -> 2.0280056 | G16: =G13/50000 -> 1.9946722 | I16: =I13/1000 -> 12.557611 | J16: =J13/5000 -> 4.7259222 | K16: =K13/10000 -> 4.5592556 | L16: =L13/25000 -> 4.4592556 | M16: =M13/50000 -> 4.4259222
A17: Charge per User per Month | C17: =Assumptions!B30 -> 15 | D17: =Assumptions!B30 -> 15 | E17: =Assumptions!B30 -> 15 | F17: =Assumptions!B30 -> 15 | G17: =Assumptions!B30 -> 15 | I17: =Assumptions!B31 -> 25 | J17: =Assumptions!B31 -> 25 | K17: =Assumptions!B31 -> 25 | L17: =Assumptions!B31 -> 25 | M17: =Assumptions!B31 -> 25
A18: Gross Margin per User | C18: =C17-C16 -> 4.8736389 | D18: =D17-D16 -> 12.705328 | E18: =E17-E16 -> 12.871994 | F18: =F17-F16 -> 12.971994 | G18: =G17-G16 -> 13.005328 | I18: =I17-I16 -> 12.442389 | J18: =J17-J16 -> 20.274078 | K18: =K17-K16 -> 20.440744 | L18: =L17-L16 -> 20.540744 | M18: =M17-M16 -> 20.574078
A19: Gross Margin % | C19: =IF(Assumptions!B30=0,0,C18/Assumptions!B30) -> 0.32490926 | D19: =IF(Assumptions!B30=0,0,D18/Assumptions!B30) -> 0.84702185 | E19: =IF(Assumptions!B30=0,0,E18/Assumptions!B30) -> 0.85813296 | F19: =IF(Assumptions!B30=0,0,F18/Assumptions!B30) -> 0.86479963 | G19: =IF(Assumptions!B30=0,0,G18/Assumptions!B30) -> 0.86702185 | I19: =IF(Assumptions!B31=0,0,I18/Assumptions!B31) -> 0.49769556 | J19: =IF(Assumptions!B31=0,0,J18/Assumptions!B31) -> 0.81096311 | K19: =IF(Assumptions!B31=0,0,K18/Assumptions!B31) -> 0.81762978 | L19: =IF(Assumptions!B31=0,0,L18/Assumptions!B31) -> 0.82162978 | M19: =IF(Assumptions!B31=0,0,M18/Assumptions!B31) -> 0.82296311
A20: Monthly Gross Profit ($) | C20: =C18*1000 -> 4873.6389 | D20: =D18*5000 -> 63526.639 | E20: =E18*10000 -> 128719.94 | F20: =F18*25000 -> 324299.86 | G20: =G18*50000 -> 650266.39 | I20: =I18*1000 -> 12442.389 | J20: =J18*5000 -> 101370.39 | K20: =K18*10000 -> 204407.44 | L20: =L18*25000 -> 513518.61 | M20: =M18*50000 -> 1028703.9
A21: Annual Gross Profit ($) | C21: =C20*12 -> 58483.667 | D21: =D20*12 -> 762319.67 | E21: =E20*12 -> 1544639.3 | F21: =F20*12 -> 3891598.3 | G21: =G20*12 -> 7803196.7 | I21: =I20*12 -> 149308.67 | J21: =J20*12 -> 1216444.7 | K21: =K20*12 -> 2452889.3 | L21: =L20*12 -> 6162223.3 | M21: =M20*12 -> 12344447
A22: Free Trial Cost (2 months) | C22: =C16*1000*Assumptions!B32 -> 20252.722 | D22: =D16*5000*Assumptions!B32 -> 22946.722 | E22: =E16*10000*Assumptions!B32 -> 42560.111 | F22: =F16*25000*Assumptions!B32 -> 101400.28 | G22: =G16*50000*Assumptions!B32 -> 199467.22 | I22: =I16*1000*Assumptions!B32 -> 25115.222 | J22: =J16*5000*Assumptions!B32 -> 47259.222 | K22: =K16*10000*Assumptions!B32 -> 91185.111 | L22: =L16*25000*Assumptions!B32 -> 222962.78 | M22: =M16*50000*Assumptions!B32 -> 442592.22
A23: Net Annual Profit (after free trial) | C23: =C21-C22 -> 38230.944 | D23: =D21-D22 -> 739372.94 | E23: =E21-E22 -> 1502079.2 | F23: =F21-F22 -> 3790198.1 | G23: =G21-G22 -> 7603729.4 | I23: =I21-I22 -> 124193.44 | J23: =J21-J22 -> 1169185.4 | K23: =K21-K22 -> 2361704.2 | L23: =L21-L22 -> 5939260.6 | M23: =M21-M22 -> 11901854

Sheet Margin Playbook
A1: CERBYL MARGIN PLAYBOOK INTERACTIVE SCENARIO
A2: Inputs (change blue cells)
A3: Parameter | B3: Value | C3: Notes
A4: Monthly Active Users | B4: 2000 | C4: Your current or projected user base
A5: Tokens per user per month | B5: 500000 | C5: 500K = Pro user, 3M = Power user
A6: % tokens on Haiku | B6: 0.9 | C6: 90% fast model, 10% Sonnet for media notes
A7: Monthly charge per user ($) | B7: 15 | C7: 15 = Pro plan, 25 = Power plan
A8: Cost Breakdown
A9: Cost Category | B9: Monthly ($) | C9: Per User ($) | D9: % of Total | E9: Nature
A10: AI Tokens (Haiku + Sonnet) | B10: =B4*B5*(B6*Assumptions!B6+(1-B6)*Assumptions!B7) -> 385 | C10: =B10/B4 -> 0.1925 | D10: =IF(B20=0,0,B10/B20) -> 0.036387312 | E10: Variable
A11: Compute and Processing | B11: =B4*Assumptions!B11*Assumptions!B12 -> 226 | C11: =B11/B4 -> 0.113 | D11: =IF(B20=0,0,B11/B20) -> 0.021359825 | E11: Variable
A12: Storage and Databases | B12: =B4*Assumptions!B13*Assumptions!B14 -> 90 | C12: =B12/B4 -> 0.045 | D12: =IF(B20=0,0,B12/B20) -> 0.0085061249 | E12: Variable
A13: Bandwidth and CDN | B13: =B4*Assumptions!B16*Assumptions!B17 -> 90 | C13: =B13/B4 -> 0.045 | D13: =IF(B20=0,0,B13/B20) -> 0.0085061249 | E13: Variable
A14: Software Licenses | B14: =ROUNDUP(B4/Assumptions!B20,0)*Assumptions!B19 -> 750 | C14: =B14/B4 -> 0.375 | D14: =IF(B20=0,0,B14/B20) -> 0.070884374 | E14: Fixed
A15: Salary (Eng and Support) | B15: =ROUNDUP(B4/Assumptions!B20,0)*Assumptions!B22*Assumptions!B23/12 -> 4761.8333 | C15: =B15/B4 -> 2.3809167 | D15: =IF(B20=0,0,B15/B20) -> 0.45005277 | E15: Semi-fixed
A16: Laptops and Equipment | B16: =ROUNDUP(B4/Assumptions!B20,0)*Assumptions!B22*Assumptions!B26/36 -> 111.11111 | C16: =B16/B4 -> 0.055555556 | D16: =IF(B20=0,0,B16/B20) -> 0.010501389 | E16: Semi-fixed
A17: Compliance and Admin | B17: =Assumptions!B24/12 -> 1666.6667 | C17: =B17/B4 -> 0.83333333 | D17: =IF(B20=0,0,B17/B20) -> 0.15752083 | E17: Fixed
A18: Facilities | B18: =ROUNDUP(B4/Assumptions!B20,0)*Assumptions!B28 -> 2500 | C18: =B18/B4 -> 1.25 | D18: =IF(B20=0,0,B18/B20) -> 0.23628125 | E18: Semi-fixed
A20: Total Monthly Cost | B20: =SUM(B10:B19) -> 10580.611 | C20: =B20/B4 -> 5.2903056 | D20: 1
A21: Unit Economics Summary
A22: Cost per User per Month | B22: =B20/B4 -> 5.2903056
A23: Charge per User per Month | B23: =B7 -> 15
A24: Gross Margin per User | B24: =B23-B22 -> 9.7096944
A25: Gross Margin % | B25: =IF(B7=0,0,(B7-B20/B4)/B7) -> 0.64731296
A26: Monthly Gross Profit | B26: =(B23-B22)*B4 -> 19419.389
A27: Annual Gross Profit | B27: =B26*12 -> 233032.67
A28: Free Trial Cost (2 months) | B28: =B20/B4*B4*Assumptions!B32 -> 21161.222
A29: Net Annual Profit | B29: =B27-B28 -> 211871.44
A31: Color Legend
A32: BLUE TEXT | B32: Hardcoded inputs change these to model scenarios
A33: GREEN TEXT | B33: Formulas pulling from Assumptions tab
A34: DARK TEXT | B34: Calculated values do not edit directly
A35: GREEN FILL | B35: Positive margin and key profit metrics
A36: ORANGE FILL | B36: Cash drag items to watch
